<?xml version="1.0" encoding="UTF-8"?><items hlblockUid="VkladCalc"><item><field name="UF_VKLAD_ID"><value>38</value></field><field name="UF_START_SUM"><value>10000</value></field><field name="UF_END_SUM"><value>3000000</value></field><field name="UF_CURRENCY"><value>RUB</value></field><field name="UF_DAYS"><value>91</value></field><field name="UF_PERCENT"><value>5</value></field></item><item><field name="UF_VKLAD_ID"><value>38</value></field><field name="UF_START_SUM"><value>10000</value></field><field name="UF_END_SUM"><value>3000000</value></field><field name="UF_CURRENCY"><value>RUB</value></field><field name="UF_DAYS"><value>181</value></field><field name="UF_PERCENT"><value>5</value></field></item><item><field name="UF_VKLAD_ID"><value>38</value></field><field name="UF_START_SUM"><value>10000</value></field><field name="UF_END_SUM"><value>3000000</value></field><field name="UF_CURRENCY"><value>RUB</value></field><field name="UF_DAYS"><value>275</value></field><field name="UF_PERCENT"><value>5</value></field></item><item><field name="UF_VKLAD_ID"><value>38</value></field><field name="UF_START_SUM"><value>10000</value></field><field name="UF_END_SUM"><value>3000000</value></field><field name="UF_CURRENCY"><value>RUB</value></field><field name="UF_DAYS"><value>367</value></field><field name="UF_PERCENT"><value>5</value></field></item><item><field name="UF_VKLAD_ID"><value>38</value></field><field name="UF_START_SUM"><value>10000</value></field><field name="UF_END_SUM"><value>3000000</value></field><field name="UF_CURRENCY"><value>RUB</value></field><field name="UF_DAYS"><value>549</value></field><field name="UF_PERCENT"><value>5</value></field></item></items>